README.rst
setup.py
ThunderParser/__init__.py
ThunderParser/parser_flashget.py
ThunderParser/parser_qqdl.py
ThunderParser/parser_thunder.py
ThunderParser.egg-info/PKG-INFO
ThunderParser.egg-info/SOURCES.txt
ThunderParser.egg-info/dependency_links.txt
ThunderParser.egg-info/top_level.txt
test/test_parser.py