Metadata-Version: 1.1
Name: ThunderParser
Version: 0.14.1
Summary: Parse the software of thunder,qqdl and flashget download url
Home-page: https://github.com/yafeile/ThunderParser
Author: fly
Author-email: yafeile@sohu.com
License: BSD License
Keywords: download,parser
Platform: Posix
Platform: Mac OS
Platform: Windows
Classifier: License :: OSI Approved :: BSD License
Classifier: Programming Language :: Python
